{"total": "9", "productId": "46823", "priceUnit": "chi\u1ebfc", "marketPrice": "38990000", "price": "28900000", "productName": "Laptop LG Gram Style 2023 14Z90RS-G.AH54A5 (Intel Core i5-1340P | 16GB | 512GB | Intel Iris Xe | 14-inch WQXGA+ | Win 11 | Tr\u1eafng)", "productSummary": "CPU: Intel Core i5-1340P (12 Cores: 4P + 8E, P: 1.9 up to 4.6 GHz / E: 1.4 up to 3.4 GHz), 12MB\r\nRAM: 16GB LPDDR5 (Dual Channel, 6000MHz)\r\n\u1ed4 c\u1ee9ng: 512GB NVMe Gen 4 SSD \r\nVGA: Intel Iris Xe Graphics\r\nM\u00e0n h\u00ecnh: 14-inch WQXGA+ (2880*1800)16:10 Anti Glare Low Refrection, OLED, 90Hz, 0.2ms, DCI-P3 99% (Typical, min 95%), 400nit, 1,000,000 :1\r\nPin: 72Wh\r\nC\u00e2n n\u1eb7ng: 999g\r\nM\u00e0u s\u1eafc: Tr\u1eafng\r\nOS: Windows 11 Home \r\n", "productUrl": "https://www.anphatpc.com.vn//laptop-lg-gram-style-2023-14z90rs-g.ah54a5-intel-core-i5-1340p.html", "image": "https://anphat.com.vn/media/product/46823_44920_laptop_lg_gram_2023_14z90rs_g_ah54a5__3_.jpg"}